{
  "project_info": {
    "project_number": "168656811240",
    "project_id": "hypeeo-e8c03",
    "storage_bucket": "hypeeo-e8c03.appspot.com"
  },
  "client": [
    {
      "client_info": {
        "mobilesdk_app_id": "1:168656811240:android:a5dc00024b9c3bfe37c55d",
        "android_client_info": {
          "package_name": "com.hypeeo.app"
        }
      },
      "oauth_client": [
        {
          "client_id": "168656811240-r2lmi9epnlk6h9ngvcbc8r01g6tcmng6.apps.googleusercontent.com",
          "client_type": 3
        }
      ],
      "api_key": [
        {
          "current_key": "AIzaSyChBZb1nsAf0RqKjVz_ogCWJVEbuW1KTUE"
        }
      ],
      "services": {
        "appinvite_service": {
          "other_platform_oauth_client": [
            {
              "client_id": "168656811240-r2lmi9epnlk6h9ngvcbc8r01g6tcmng6.apps.googleusercontent.com",
              "client_type": 3
            },
            {
              "client_id": "168656811240-v205g1qbcfgbh3ckcdoe1aq0mbglggf8.apps.googleusercontent.com",
              "client_type": 2,
              "ios_info": {
                "bundle_id": "com.hypeeo.app"
              }
            }
          ]
        }
      }
    }
  ],
  "configuration_version": "1"
}